gltfio/__init__.py
gltfio/_version.py
gltfio/glb.py
gltfio/parser.py
gltfio/types.py
pygltfio-0.6.0.dist-info/LICENSE
pygltfio-0.6.0.dist-info/METADATA
pygltfio-0.6.0.dist-info/WHEEL
pygltfio-0.6.0.dist-info/top_level.txt
pygltfio-0.6.0.dist-info/RECORD
